[
    {
      "id": "6560b32d310f01bece6efc29",
      "price": 20,
      "name": "Francisca Cook"
    },
    {
      "id": "6560b32d3e52478fe0c42985",
      "price": 36,
      "name": "Joyce Torres"
    },
    {
      "id": "6560b32db83ec9ebcb5c54d9",
      "price": 31,
      "name": "Cross Chase"
    },
    {
      "id": "6560b32dc3a9c73025b57c00",
      "price": 28,
      "name": "Chavez Glenn"
    },
    {
      "id": "6560b32dcd40746ea199d9ca",
      "price": 34,
      "name": "English Hill"
    },
    {
      "id": "6560b32d2cea6d3975a3c1b6",
      "price": 22,
      "name": "Tanya England"
    }
  ]